tcrdist/__init__.py
tcrdist/adpt_funcs.py
tcrdist/automate.py
tcrdist/background.py
tcrdist/breadth.py
tcrdist/centers.py
tcrdist/diversity.py
tcrdist/ecdf.py
tcrdist/gene_pairing_plot.py
tcrdist/html_colors.py
tcrdist/join.py
tcrdist/mappers.py
tcrdist/memory.py
tcrdist/neighbors.py
tcrdist/olga_directed.py
tcrdist/olga_load_model.py
tcrdist/paths.py
tcrdist/pgen.py
tcrdist/plotting.py
tcrdist/public.py
tcrdist/regex.py
tcrdist/rep_diff.py
tcrdist/rep_funcs.py
tcrdist/repertoire.py
tcrdist/repertoire_db.py
tcrdist/sample.py
tcrdist/setup_tests.py
tcrdist/sparse.py
tcrdist/speed.py
tcrdist/summarize.py
tcrdist/swap_gene_name.py
tcrdist/tabulate.py
tcrdist/translation.py
tcrdist/tree.py
tcrdist/vdjtools_funcs.py
tcrdist/data/__init__.py
tcrdist/data/covid19/__init__.py
tcrdist/data/covid19/m60_bkgd_test_input.csv
tcrdist/data/covid19/m60_test_input.csv
tcrdist/data/covid19/mira_epitope_10_2274_LSPRWYFYY_SPRWYFYYL.tcrdist3.csv
tcrdist/data/covid19/mira_epitope_110_148_ELIRQGTDY_QELIRQGTDY_QELIRQGTDYKHW.tcrdist3.csv
tcrdist/data/covid19/mira_epitope_111_146_AEIPKEEVKPF_ASKIITLKK_SASKIITLK.tcrdist3.csv
tcrdist/data/covid19/mira_epitope_118_136_ALNTPKDHI_ATEGALNTPK.tcrdist3.csv
tcrdist/data/covid19/mira_epitope_133_102_NQKLIANQF.tcrdist3.csv
tcrdist/data/covid19/mira_epitope_140_92_NSSPDDQIGY_NTNSSPDDQIGYY_SSPDDQIGY_SSPDDQIGYY.tcrdist3.csv
tcrdist/data/covid19/mira_epitope_147_73_DLFMRIFTI_MDLFMRIFTI.tcrdist3.csv
tcrdist/data/covid19/mira_epitope_155_59_RARSVSPKL_SVSPKLFIR.tcrdist3.csv
tcrdist/data/covid19/mira_epitope_16_1683_QYIKWPWYI_YEQYIKWPW_YEQYIKWPWY.tcrdist3.csv
tcrdist/data/covid19/mira_epitope_176_44_SSTFNVPMEKLK.tcrdist3.csv
tcrdist/data/covid19/mira_epitope_183_39_RIRGGDGKM_RIRGGDGKMK.tcrdist3.csv
tcrdist/data/covid19/mira_epitope_185_39_ASQRVAGDSGFAAY_DSGFAAYSR_VAGDSGFAAY.tcrdist3.csv
tcrdist/data/covid19/mira_epitope_18_1578_FPNITNLCPF_QPTESIVRF_RFPNITNLCPF_TESIVRFPNI_VQPTESIVRF_VRFPNITNL.tcrdist3.csv
tcrdist3-0.3.dist-info/LICENSE
tcrdist3-0.3.dist-info/METADATA
tcrdist3-0.3.dist-info/WHEEL
tcrdist3-0.3.dist-info/top_level.txt
tcrdist3-0.3.dist-info/RECORD
