Metadata-Version: 2.1
Name: tcrdist3
Version: 0.3
Summary: flexible distance measures for comparing T cell receptors
Home-page: https://github.com/kmayerb/tcrdist3
Author: Koshlan Mayer-Blackwell
Author-email: kmayerbl@fredhutch.org
Maintainer: Koshlan Mayer-Blackwell
Maintainer-email: kmayerbl@fredhutch.org
License: MIT
License-File: LICENSE
Requires-Dist: pandas >=0.24.2
Requires-Dist: numpy >=1.16.4
Requires-Dist: parasail >=1.1.17
Requires-Dist: scipy >=1.4.1
Requires-Dist: pwseqdist >=0.6
Requires-Dist: numba
Requires-Dist: zipdist >=0.1.5
Requires-Dist: fishersapi
Requires-Dist: hierdiff >=0.4
Requires-Dist: palmotif >=0.2
Requires-Dist: tcrsampler >=0.1.9
Requires-Dist: parmap >=1.5.2
Requires-Dist: olga >=1.2.1
Requires-Dist: dill >=0.3.2
